<?xml version="1.0" encoding="utf-8"?>
<Maps>
  <Map Type="Ground_BLD" Name="ASMGCS_NWWW_BLD" Priority="1" Center="-220052.000+1661247.000">
    <Infill Name="terminal">
      <Point>
-220045.912+1661301.415/
-220046.047+1661300.645/
-220046.414+1661300.119/
-220046.887+1661259.785/
-220047.579+1661259.660/
-220048.441+1661259.913/
-220050.895+1661304.327/
-220048.426+1661305.847/
-220045.912+1661301.415
</Point>
    </Infill>
    <Infill Name="building1">
      <Point>
-220050.546+1661307.082/
-220051.093+1661308.085/
-220052.533+1661307.158/
-220051.937+1661306.150/
-220050.546+1661307.082
</Point>
    </Infill>
    <Infill Name="building2">
      <Point>
-220051.880+1661308.786/
-220053.966+1661307.398/
-220055.450+1661310.009/
-220053.326+1661311.330/
-220051.880+1661308.786
</Point>
    </Infill>
    <Infill Name="building3">
      <Point>
-220104.506+1661245.566/
-220105.692+1661244.791/
-220106.722+1661246.624/
-220105.538+1661247.397/
-220104.506+1661245.566
</Point>
    </Infill>
    <Infill Name="building4">
      <Point>
-220105.838+1661247.825/
-220106.761+1661249.477/
-220107.741+1661248.878/
-220106.797+1661247.190/
-220105.838+1661247.825
</Point>
    </Infill>
    <Infill Name="building5">
      <Point>
-220107.162+1661250.154/
-220108.041+1661249.573/
-220108.922+1661251.132/
-220108.037+1661251.683/
-220107.162+1661250.154
</Point>
    </Infill>
    <Infill Name="building6">
      <Point>
-220108.810+1661253.198/
-220109.620+1661252.640/
-220110.443+1661254.109/
-220109.628+1661254.576/
-220108.810+1661253.198
</Point>
    </Infill>
  </Map>
  <Map Type="Ground_APR" Name="ASMGCS_NWWW_APR" Priority="3" Center="-220052.000+1661247.000">
    <Infill Name="apron_1">
      <Point>
-220043.539+1661257.844/
-220048.618+1661254.579/
-220049.982+1661257.038/
-220044.920+1661300.292/
-220043.539+1661257.844
</Point>
    </Infill>
    <Infill Name="apron_2">
      <Point>
-220056.173+1661305.635/
-220055.940+1661306.247/
-220055.702+1661306.488/
-220056.989+1661308.056/
-220056.995+1661308.335/
-220057.014+1661308.537/
-220057.125+1661308.772/
-220057.777+1661309.942/
-220056.928+1661310.489/
-220056.544+1661309.822/
-220055.848+1661310.283/
-220049.833+1661259.261/
-220049.722+1661259.072/
-220049.708+1661259.000/
-220049.776+1661258.846/
-220049.919+1661258.703/
-220051.799+1661257.545/
-220056.112+1661305.273/
-220056.173+1661305.635
</Point>
    </Infill>
    <Infill Name="apron_military">
      <Point>
-220101.015+1661247.130/
-220104.164+1661245.015/
-220109.607+1661254.670/
-220109.799+1661254.530/
-220110.289+1661255.406/
-220108.657+1661256.481/
-220107.214+1661253.928/
-220107.008+1661253.737/
-220106.786+1661253.661/
-220106.559+1661253.667/
-220106.359+1661253.731/
-220106.011+1661253.918/
-220105.769+1661253.473/
-220105.900+1661253.350/
-220106.033+1661253.068/
-220106.080+1661252.770/
-220106.020+1661252.417/
-220103.992+1661248.837/
-220103.298+1661249.281/
-220102.448+1661247.733/
-220102.216+1661247.488/
-220102.009+1661247.389/
-220101.751+1661247.352/
-220101.497+1661247.413/
-220101.249+1661247.539/
-220101.015+1661247.130
</Point>
    </Infill>
  </Map>
  <Map Type="Ground_TWY" Name="ASMGCS_NWWW_TWY" Priority="2" Center="-220052.000+1661247.000">
    <Infill Name="taxiway_BW">
      <Point>
-220054.559+1661252.251/
-220054.232+1661251.771/
-220053.933+1661251.461/
-220053.582+1661251.273/
-220053.152+1661251.164/
-220052.722+1661251.174/
-220052.380+1661251.266/
-220052.035+1661251.515/
-220051.802+1661251.826/
-220051.648+1661252.140/
-220051.596+1661252.451/
-220051.638+1661252.851/
-220051.768+1661253.370/
-220051.871+1661253.623/
-220053.329+1661256.649/
-220052.506+1661257.124/
-220052.272+1661256.468/
-220051.227+1661254.636/
-220050.581+1661253.663/
-220050.333+1661253.382/
-220050.038+1661253.220/
-220049.819+1661253.170/
-220049.382+1661253.242/
-220049.013+1661253.428/
-220048.544+1661253.667/
-220048.541+1661254.437/
-220048.650+1661254.652/
-220043.591+1661257.932/
-220043.060+1661256.975/
-220041.834+1661257.755/
-220041.438+1661257.072/
-220045.489+1661254.463/
-220046.667+1661253.683/
-220048.478+1661252.549/
-220050.940+1661250.713/
-220051.442+1661250.350/
-220051.800+1661250.071/
-220051.980+1661249.840/
-220052.149+1661249.553/
-220052.275+1661249.141/
-220052.313+1661248.751/
-220052.270+1661248.365/
-220052.151+1661247.953/
-220052.012+1661247.658/
-220054.722+1661252.483/
-220054.559+1661252.251
</Point>
    </Infill>
    <Infill Name="taxiway_CW">
      <Point>
-220054.720+1661258.932/
-220055.052+1661259.170/
-220055.435+1661259.314/
-220055.883+1661259.354/
-220056.283+1661259.300/
-220056.587+1661259.170/
-220056.777+1661258.994/
-220056.960+1661258.755/
-220057.072+1661258.547/
-220057.215+1661258.193/
-220057.271+1661257.729/
-220057.238+1661257.314/
-220057.139+1661256.842/
-220056.937+1661256.325/
-220059.502+1661300.903/
-220059.011+1661300.203/
-220058.744+1661259.935/
-220058.397+1661259.737/
-220058.092+1661259.624/
-220057.769+1661259.618/
-220057.434+1661259.676/
-220057.130+1661259.790/
-220056.877+1661259.945/
-220056.545+1661300.349/
-220056.376+1661300.648/
-220056.274+1661300.993/
-220056.231+1661301.377/
-220056.264+1661301.710/
-220056.432+1661302.164/
-220056.686+1661302.639/
-220057.375+1661303.845/
-220057.594+1661304.317/
-220057.775+1661304.885/
-220057.825+1661305.590/
-220057.797+1661306.026/
-220057.664+1661306.597/
-220057.206+1661307.562/
-220057.058+1661307.869/
-220057.000+1661308.026/
-220056.993+1661308.122/
-220055.651+1661306.478/
-220055.822+1661306.318/
-220055.969+1661306.115/
-220056.057+1661305.917/
-220056.117+1661305.668/
-220056.101+1661305.384/
-220055.960+1661305.058/
-220051.740+1661257.585/
-220053.315+1661256.623/
-220054.504+1661258.692/
-220054.720+1661258.932
</Point>
    </Infill>
    <Infill Name="taxiway_G">
      <Point>
-220104.663+1661254.777/
-220100.175+1661257.783/
-220100.052+1661257.940/
-220059.934+1661258.167/
-220059.904+1661258.370/
-220059.935+1661258.685/
-220100.168+1661259.313/
-220058.693+1661256.691/
-220059.016+1661257.094/
-220059.207+1661257.248/
-220059.385+1661257.317/
-220059.643+1661257.355/
-220059.886+1661257.308/
-220103.803+1661254.804/
-220103.937+1661254.627/
-220103.930+1661254.477/
-220103.719+1661254.000/
-220103.686+1661253.785/
-220103.696+1661253.574/
-220103.738+1661253.389/
-220103.820+1661253.207/
-220103.932+1661252.985/
-220104.194+1661253.426/
-220104.138+1661253.648/
-220104.132+1661253.834/
-220104.198+1661254.008/
-220104.284+1661254.132/
-220104.443+1661254.258/
-220104.536+1661254.292/
-220104.663+1661254.777
</Point>
    </Infill>
    <Infill Name="taxiway_G-Runupbay">
      <Point>
-220103.896+1661253.052/
-220103.990+1661252.871/
-220104.066+1661252.677/
-220103.833+1661252.278/
-220104.500+1661251.816/
-220104.608+1661251.772/
-220104.697+1661251.789/
-220104.764+1661251.838/
-220104.804+1661251.909/
-220105.464+1661253.042/
-220105.561+1661252.982/
-220106.072+1661253.881/
-220104.621+1661254.802/
-220104.411+1661254.365/
-220104.897+1661254.059/
-220104.943+1661253.900/
-220104.898+1661253.750/
-220104.614+1661253.246/
-220104.476+1661253.237/
-220104.263+1661253.361/
-220104.182+1661253.442/
-220103.896+1661253.052
</Point>
    </Infill>
    <Infill Name="taxiway_T">
      <Point>
-220054.806+1661249.755/
-220055.098+1661250.132/
-220055.295+1661250.274/
-220055.413+1661250.329/
-220055.687+1661250.389/
-220055.908+1661250.357/
-220056.213+1661250.263/
-220101.032+1661247.111/
-220101.275+1661247.533/
-220056.435+1661250.657/
-220056.213+1661250.928/
-220056.070+1661251.254/
-220056.037+1661251.562/
-220056.078+1661251.861/
-220056.192+1661252.234/
-220054.806+1661249.755
</Point>
    </Infill>
  </Map>
  <Map Type="Ground_RWY" Name="ASMGCS_NWWW_RWY" Priority="1" Center="-220052.000+1661247.000">
    <Infill Name="runway_RW11/29">
      <Point>
-220120.280+1661334.911/
-220119.013+1661335.734/
-220118.689+1661335.821/
-220118.200+1661335.782/
-220117.856+1661335.623/
-220117.573+1661335.347/
-220117.420+1661335.074/
-220117.620+1661334.142/
-220117.641+1661333.756/
-220117.587+1661333.325/
-220117.482+1661333.005/
-220025.942+1661201.389/
-220025.598+1661201.093/
-220025.289+1661200.898/
-220024.888+1661200.726/
-220024.520+1661200.622/
-220024.257+1661200.537/
-220024.118+1661200.319/
-220023.996+1661159.995/
-220023.968+1661159.675/
-220024.000+1661159.380/
-220024.100+1661159.139/
-220024.208+1661158.950/
-220024.424+1661158.709/
-220025.663+1661157.895/
-220120.280+1661334.911
</Point>
    </Infill>
  </Map>
</Maps>